stackhut-0.6.1.dist-info/DESCRIPTION.rst
stackhut-0.6.1.dist-info/METADATA
stackhut-0.6.1.dist-info/RECORD
stackhut-0.6.1.dist-info/WHEEL
stackhut-0.6.1.dist-info/entry_points.txt
stackhut-0.6.1.dist-info/metadata.json
stackhut-0.6.1.dist-info/top_level.txt
stackhut_toolkit/__init__.py
stackhut_toolkit/__main__.py
stackhut_toolkit/builder.py
stackhut_toolkit/commands.py
stackhut_toolkit/toolkit_utils.py
stackhut_toolkit/common/__init__.py
stackhut_toolkit/common/commands.py
stackhut_toolkit/common/config.py
stackhut_toolkit/common/exceptions.py
stackhut_toolkit/common/utils.py
stackhut_toolkit/common/barrister/__init__.py
stackhut_toolkit/common/barrister/exceptions.py
stackhut_toolkit/common/barrister/parser.py
stackhut_toolkit/common/barrister/runtime.py
stackhut_toolkit/common/barrister/cythonplex3/Actions.py
stackhut_toolkit/common/barrister/cythonplex3/DFA.py
stackhut_toolkit/common/barrister/cythonplex3/Errors.py
stackhut_toolkit/common/barrister/cythonplex3/Lexicons.py
stackhut_toolkit/common/barrister/cythonplex3/Machines.py
stackhut_toolkit/common/barrister/cythonplex3/Regexps.py
stackhut_toolkit/common/barrister/cythonplex3/Scanners.py
stackhut_toolkit/common/barrister/cythonplex3/Timing.py
stackhut_toolkit/common/barrister/cythonplex3/Traditional.py
stackhut_toolkit/common/barrister/cythonplex3/Transitions.py
stackhut_toolkit/common/barrister/cythonplex3/__init__.py
stackhut_toolkit/common/runtime/__init__.py
stackhut_toolkit/common/runtime/backends.py
stackhut_toolkit/common/runtime/rpc.py
stackhut_toolkit/common/runtime/runner.py
stackhut_toolkit/common/runtime/runtime_server.py
stackhut_toolkit/res/scaffold/common/.gitignore
stackhut_toolkit/res/scaffold/common/Hutfile.yaml
stackhut_toolkit/res/scaffold/common/README.md
stackhut_toolkit/res/scaffold/common/api.idl
stackhut_toolkit/res/scaffold/common/test_request.json
stackhut_toolkit/res/scaffold/nodejs/app.js
stackhut_toolkit/res/scaffold/python/app.py
stackhut_toolkit/res/scaffold/python/requirements.txt
stackhut_toolkit/res/shims/nodejs/runner.js
stackhut_toolkit/res/shims/nodejs/stackhut.js
stackhut_toolkit/res/shims/python/runner.py
stackhut_toolkit/res/shims/python/stackhut.py
