Metadata-Version: 2.0
Name: stackhut
Version: 0.6.1
Summary: Deploy classes as Microservices
Home-page: https://github.com/stackhut/stackhut-toolkit
Author: StackHut
Author-email: stackhut@stackhut.com
License: Apache
Keywords: stackhut
Platform: POSIX
Classifier: Development Status :: 2 - Pre-Alpha
Classifier: Intended Audience :: Developers
Classifier: Environment :: Console
Classifier: Natural Language :: English
Classifier: License :: OSI Approved :: Apache Software License
Classifier: Operating System :: OS Independent
Classifier: Programming Language :: Python
Classifier: Programming Language :: Python :: 3
Classifier: Programming Language :: Python :: 3.4
Classifier: Topic :: Software Development
Requires-Dist: PyYaml
Requires-Dist: arrow
Requires-Dist: colorlog
Requires-Dist: docker-py
Requires-Dist: jinja2
Requires-Dist: json-rpc
Requires-Dist: multipledispatch
Requires-Dist: requests
Requires-Dist: sh
Requires-Dist: stackhut-client (>=0.1.1)
Requires-Dist: werkzeug
